notetiktok/__init__.py
notetiktok/data/__init__.py
notetiktok/data/base.py
notetiktok/data/core.py
notetiktok/data/mock.py
notetiktok/data/web1.py
notetiktok/server/__init__.py
notetiktok/server/data_service.py
notetiktok/server/merge.py
notetiktok/server/cron/__init__.py
notetiktok/server/cron/script.py
notetiktok/server/cron/server.py
notetiktok-0.1.16.dist-info/METADATA
notetiktok-0.1.16.dist-info/WHEEL
notetiktok-0.1.16.dist-info/entry_points.txt
notetiktok-0.1.16.dist-info/top_level.txt
notetiktok-0.1.16.dist-info/RECORD
